medflux/__init__.py
medflux/datasets/__init__.py
medflux/datasets/data_collator.py
medflux/datasets/encoders.py
medflux/datasets/filters.py
medflux/datasets/patient_concept_stream.py
medflux/datasets/preprocessing.py
medflux/datasets/tokenizers.py
medflux/datasets/utils.py
medflux/metrics/__init__.py
medflux/metrics/next_concept_prediction.py
medflux/models/__init__.py
medflux/models/lucid_transformers.py
medflux/utils/pickle.py
medflux-0.1.4.dist-info/METADATA
medflux-0.1.4.dist-info/WHEEL
medflux-0.1.4.dist-info/top_level.txt
medflux-0.1.4.dist-info/RECORD
